my/__init__.py
my/client.py
mypypi_client-0.0.9.dist-info/DESCRIPTION.rst
mypypi_client-0.0.9.dist-info/METADATA
mypypi_client-0.0.9.dist-info/RECORD
mypypi_client-0.0.9.dist-info/WHEEL
mypypi_client-0.0.9.dist-info/metadata.json
mypypi_client-0.0.9.dist-info/top_level.txt
